chinese_chess_lib/__init__.py
chinese_chess_lib/__init__.pyi
chinese_chess_lib/_core.cp310-win_arm64.pyd
chinese_chess_lib-0.3.0.dist-info/METADATA
chinese_chess_lib-0.3.0.dist-info/WHEEL
chinese_chess_lib-0.3.0.dist-info/licenses/LICENSE
chinese_chess_lib-0.3.0.dist-info/RECORD
