Metadata-Version: 2.4
Name: chinese_chess_lib
Version: 0.3.0
Summary: A library include some rules of chinese chess(Xiangqi).
Author-Email: Liang Chenxuan <abcsss2035@gmail.com>
License-Expression: GPL-3.0
License-File: LICENSE
Classifier: Development Status :: 4 - Beta
Classifier: Programming Language :: Python :: 3 :: Only
Classifier: Programming Language :: Python :: 3.10
Classifier: Programming Language :: Python :: 3.11
Classifier: Programming Language :: Python :: 3.12
Classifier: Programming Language :: Python :: 3.13
Requires-Python: >=3.9
